{
	"id": "2a1f6427-3de3-4792-9b30-0705653e267d",
	"name": "LOCAL",
	"values": [
		{
			"key": "access_token",
			"value": "a",
			"enabled": true
		},
		{
			"key": "refresh_token",
			"value": "a",
			"enabled": true
		},
		{
			"key": "provision",
			"value": "localhost:8080",
			"type": "default",
			"enabled": true
		},
		{
			"key": "shoppingcartcheckout",
			"value": "localhost:8080",
			"type": "default",
			"enabled": true
		},
		{
			"key": "si-authorization",
			"value": "localhost:8080",
			"type": "default",
			"enabled": true
		},
		{
			"key": "ui-backend",
			"value": "localhost:8080",
			"type": "default",
			"enabled": true
		},
		{
			"key": "si-user-token",
			"value": "localhost:8080",
			"type": "default",
			"enabled": true
		},
		{
			"key": "biztalk-tmf-api",
			"value": "localhost:8080",
			"type": "default",
			"enabled": true
		},
		{
			"key": "order-create-service",
			"value": "localhost:8080",
			"type": "default",
			"enabled": true
		},
		{
			"key": "payment-methods",
			"value": "localhost:8080",
			"type": "default",
			"enabled": true
		},
		{
			"key": "si-bpmn",
			"value": "localhost:9090",
			"type": "default",
			"enabled": true
		},
		{
			"key": "northbound",
			"value": "localhost:8080",
			"type": "default",
			"enabled": true
		},
		{
			"key": "dacm",
			"value": "localhost:8080",
			"type": "default",
			"enabled": true
		},
		{
			"key": "aggregate",
			"value": "localhost:8080",
			"type": "default",
			"enabled": true
		},
		{
			"key": "dagm",
			"value": "localhost:8080",
			"type": "default",
			"enabled": true
		},
		{
			"key": "backoffice",
			"value": "localhost:8080",
			"type": "default",
			"enabled": true
		},
		{
			"key": "dcm",
			"value": "localhost:8080",
			"type": "default",
			"enabled": true
		},
		{
			"key": "ddms",
			"value": "localhost:8080",
			"type": "default",
			"enabled": true
		},
		{
			"key": "dgeo",
			"value": "localhost:8080",
			"type": "default",
			"enabled": true
		},
		{
			"key": "dpm",
			"value": "localhost:8080",
			"type": "default",
			"enabled": true
		},
		{
			"key": "dpam",
			"value": "localhost:8080",
			"type": "default",
			"enabled": true
		},
		{
			"key": "dpr",
			"value": "localhost:8080",
			"type": "default",
			"enabled": true
		},
		{
			"key": "dpim",
			"value": "localhost:8080",
			"type": "default",
			"enabled": true
		},
		{
			"key": "dpom",
			"value": "localhost:8080",
			"type": "default",
			"enabled": true
		},
		{
			"key": "reference",
			"value": "localhost:8080",
			"type": "default",
			"enabled": true
		},
		{
			"key": "dri",
			"value": "localhost:8080",
			"type": "default",
			"enabled": true
		},
		{
			"key": "drc",
			"value": "localhost:8080",
			"type": "default",
			"enabled": true
		},
		{
			"key": "dro",
			"value": "localhost:8080",
			"type": "default",
			"enabled": true
		},
		{
			"key": "drof",
			"value": "localhost:8080",
			"type": "default",
			"enabled": true
		},
		{
			"key": "s3",
			"value": "localhost:8080",
			"type": "default",
			"enabled": true
		},
		{
			"key": "dsc",
			"value": "localhost:8080",
			"type": "default",
			"enabled": true
		},
		{
			"key": "dso",
			"value": "localhost:8080",
			"type": "default",
			"enabled": true
		},
		{
			"key": "dsi",
			"value": "localhost:8080",
			"type": "default",
			"enabled": true
		},
		{
			"key": "dsof",
			"value": "localhost:8080",
			"type": "default",
			"enabled": true
		},
		{
			"key": "dxl1_token",
			"value": "",
			"type": "default",
			"enabled": true
		},
		{
			"key": "dxl2_token",
			"value": "",
			"type": "default",
			"enabled": true
		},
		{
			"key": "dsales",
			"value": "",
			"type": "default",
			"enabled": true
		}
	],
	"_postman_variable_scope": "environment",
	"_postman_exported_at": "2023-02-14T12:39:00.420Z",
	"_postman_exported_using": "Postman/10.9.4"
}